{
  "type": "set_meta",
  "video_id": "lghpxPhVoPo",
  "episode_title": "KT #761 (HOUSTON) - ADAM RAY + KIM CONGDON",
  "episode_url": "https://www.youtube.com/watch?v=lghpxPhVoPo",
  "publish_date": "2026-03-24",
  "guests": ["Adam Ray", "Kim Congdon"],
  "comedian_name": "Mackenzie Jewell",
  "comedian_type": "bucket_pull",
  "set_number": 6,
  "start_seconds": 2731,
  "bits": [
    {
      "bit_id": "bit_001",
      "premise": "Minority identity stacking is neutralized by whiteness, and bisexuality is ranked as gayer than homosexuality because choosing dick over pussy proves greater commitment.",
      "line_range": [1046, 1050],
      "beats": [
        {
          "beat_id": "bit_001_beat_001",
          "line_range": [1046, 1047],
          "topics": ["autism", "sexuality", "race", "privilege"]
        },
        {
          "beat_id": "bit_001_beat_002",
          "line_range": [1047, 1050],
          "topics": ["bisexuality", "gay", "sex", "sexuality"]
        }
      ]
    },
    {
      "bit_id": "bit_002",
      "premise": "Autism during sex hijacks the brain with hyperfocus on unrelated technical or intellectual topics.",
      "line_range": [1050, 1060],
      "beats": [
        {
          "beat_id": "bit_002_beat_001",
          "line_range": [1050, 1053],
          "topics": ["autism", "sex", "sensory overload", "technology"]
        },
        {
          "beat_id": "bit_002_beat_002",
          "line_range": [1056, 1060],
          "topics": ["autism", "Netflix", "sex", "movies"]
        }
      ]
    }
  ],
  "lines": [
    {"line_number": 1045, "text": "Hey, gang.", "start": 2731, "label": "fluff"},
    {"line_number": 1046, "text": "Hell yeah. I'm gay and autistic so technically I'm a double minority, but because I'm white", "start": 2733, "label": "setup"},
    {"line_number": 1047, "text": "it just levels out. You know what I mean? I'm bisexual, that kind of sucks. You know", "start": 2742, "label": "punchline"},
    {"line_number": 1048, "text": "what I mean? Because I feel like bisexual is gayer than being gay, you know? Because", "start": 2748, "label": "setup"},
    {"line_number": 1049, "text": "when you're bi that means that you like dick and pussy, right? So if you choose some dick", "start": 2753, "label": "setup"},
    {"line_number": 1050, "text": "overpussy. That's gay. That's really gay. But I'm autistic and bitches love the tism", "start": 2758, "label": "punchline"},
    {"line_number": 1051, "text": "dick. I be stimmin' in they shit, you know? I'm like, \"Damn, bitch, this pussy give me", "start": 2769, "label": "setup"},
    {"line_number": 1052, "text": "a sensory overload right now.\" I'm in the hole. I'm like, \"So when you store your", "start": 2778, "label": "setup"},
    {"line_number": 1053, "text": "Do you use Dropbox or OneDrive?", "start": 2783, "label": "punchline"},
    {"line_number": 1055, "text": "You know.", "start": 2787, "label": "fluff"},
    {"line_number": 1056, "text": "I'm really bad at Netflix and chilling,", "start": 2788, "label": "setup"},
    {"line_number": 1057, "text": "'cause I always just want to pay attention to the movie,", "start": 2789, "label": "setup"},
    {"line_number": 1058, "text": "you know?", "start": 2792, "label": "fluff"},
    {"line_number": 1059, "text": "I'm like, \"Babe, stop sucking my dick.", "start": 2793, "label": "setup"},
    {"line_number": 1060, "text": "This is the scene where Michael Keaton becomes the founder.\"", "start": 2796, "label": "punchline"},
    {"line_number": 1062, "text": "Cool.", "start": 2802, "label": "fluff"},
    {"line_number": 1063, "text": "Shut up.", "start": 2803, "label": "fluff"}
  ]
}
